[
  {
    "Id": 0,
    "Seasons": [
      "28f834e4-25bb-47e3-a7c7-f9089fbca86f"
    ],
    "Mal": {
      "Id": "41487",
      "Name": "Tensei shitara Slime Datta Ken 2nd Season Part 2",
      "ImageUrl": "https://cdn.myanimelist.net/images/anime/1033/118296.webp",
      "MemberCount": 397742,
      "Score": 831,
      "EpisodesCount": 12,
      "Status": 0
    }
  },
  {
    "Id": 0,
    "Seasons": [
      "28f834e4-25bb-47e3-a7c7-f9089fbca86f"
    ],
    "Mal": {
      "Id": "39247",
      "Name": "Kobayashi-san Chi no Maid Dragon S",
      "ImageUrl": "https://cdn.myanimelist.net/images/anime/1252/115539.webp",
      "MemberCount": 342527,
      "Score": 849,
      "EpisodesCount": 12,
      "Status": 0
    }
  },
  {
    "Id": 0,
    "Seasons": [
      "28f834e4-25bb-47e3-a7c7-f9089fbca86f"
    ],
    "Mal": {
      "Id": "46471",
      "Name": "Tantei wa Mou, Shindeiru.",
      "ImageUrl": "https://cdn.myanimelist.net/images/anime/1843/115815.webp",
      "MemberCount": 251252,
      "Score": 638,
      "EpisodesCount": 12,
      "Status": 0
    }
  },
  {
    "Id": 0,
    "Seasons": [
      "28f834e4-25bb-47e3-a7c7-f9089fbca86f"
    ],
    "Mal": {
      "Id": "48580",
      "Name": "Vanitas no Karte",
      "ImageUrl": "https://cdn.myanimelist.net/images/anime/1401/118483.webp",
      "MemberCount": 237367,
      "Score": 793,
      "EpisodesCount": 12,
      "Status": 0
    }
  },
  {
    "Id": 0,
    "Seasons": [
      "28f834e4-25bb-47e3-a7c7-f9089fbca86f"
    ],
    "Mal": {
      "Id": "43969",
      "Name": "Kanojo mo Kanojo",
      "ImageUrl": "https://cdn.myanimelist.net/images/anime/1713/117119.webp",
      "MemberCount": 217498,
      "Score": 670,
      "EpisodesCount": 12,
      "Status": 0
    }
  },
  {
    "Id": 0,
    "Seasons": [
      "28f834e4-25bb-47e3-a7c7-f9089fbca86f"
    ],
    "Mal": {
      "Id": "40904",
      "Name": "Bokutachi no Remake",
      "ImageUrl": "https://cdn.myanimelist.net/images/anime/1871/118309.webp",
      "MemberCount": 204694,
      "Score": 752,
      "EpisodesCount": 12,
      "Status": 0
    }
  },
  {
    "Id": 0,
    "Seasons": [
      "28f834e4-25bb-47e3-a7c7-f9089fbca86f"
    ],
    "Mal": {
      "Id": "41710",
      "Name": "Genjitsu Shugi Yuusha no Oukoku Saikenki",
      "ImageUrl": "https://cdn.myanimelist.net/images/anime/1240/118272.webp",
      "MemberCount": 195115,
      "Score": 721,
      "EpisodesCount": 13,
      "Status": 0
    }
  },
  {
    "Id": 0,
    "Seasons": [
      "28f834e4-25bb-47e3-a7c7-f9089fbca86f"
    ],
    "Mal": {
      "Id": "43523",
      "Name": "Tsuki ga Michibiku Isekai Douchuu",
      "ImageUrl": "https://cdn.myanimelist.net/images/anime/1950/116474.webp",
      "MemberCount": 178918,
      "Score": 775,
      "EpisodesCount": 12,
      "Status": 0
    }
  },
  {
    "Id": 0,
    "Seasons": [
      "28f834e4-25bb-47e3-a7c7-f9089fbca86f"
    ],
    "Mal": {
      "Id": "44203",
      "Name": "Seirei Gensouki",
      "ImageUrl": "https://cdn.myanimelist.net/images/anime/1453/116276.webp",
      "MemberCount": 178771,
      "Score": 703,
      "EpisodesCount": 12,
      "Status": 0
    }
  },
  {
    "Id": 0,
    "Seasons": [
      "28f834e4-25bb-47e3-a7c7-f9089fbca86f"
    ],
    "Mal": {
      "Id": "48849",
      "Name": "Sonny Boy",
      "ImageUrl": "https://cdn.myanimelist.net/images/anime/1509/117149.webp",
      "MemberCount": 157725,
      "Score": 768,
      "EpisodesCount": 12,
      "Status": 0
    }
  },
  {
    "Id": 0,
    "Seasons": [
      "28f834e4-25bb-47e3-a7c7-f9089fbca86f"
    ],
    "Mal": {
      "Id": "48753",
      "Name": "Jahy-sama wa Kujikenai!",
      "ImageUrl": "https://cdn.myanimelist.net/images/anime/1154/115599.webp",
      "MemberCount": 152032,
      "Score": 708,
      "EpisodesCount": 20,
      "Status": 0
    }
  },
  {
    "Id": 0,
    "Seasons": [
      "28f834e4-25bb-47e3-a7c7-f9089fbca86f"
    ],
    "Mal": {
      "Id": "42282",
      "Name": "Otome Game no Hametsu Flag shika Nai Akuyaku Reijou ni Tensei shiteshimatta... X",
      "ImageUrl": "https://cdn.myanimelist.net/images/anime/1088/116439.webp",
      "MemberCount": 147882,
      "Score": 728,
      "EpisodesCount": 12,
      "Status": 0
    }
  },
  {
    "Id": 0,
    "Seasons": [
      "28f834e4-25bb-47e3-a7c7-f9089fbca86f"
    ],
    "Mal": {
      "Id": "47257",
      "Name": "Shinigami Bocchan to Kuro Maid",
      "ImageUrl": "https://cdn.myanimelist.net/images/anime/1471/115593.webp",
      "MemberCount": 134152,
      "Score": 768,
      "EpisodesCount": 12,
      "Status": 0
    }
  },
  {
    "Id": 0,
    "Seasons": [
      "28f834e4-25bb-47e3-a7c7-f9089fbca86f"
    ],
    "Mal": {
      "Id": "42627",
      "Name": "Peach Boy Riverside",
      "ImageUrl": "https://cdn.myanimelist.net/images/anime/1535/115023.webp",
      "MemberCount": 120935,
      "Score": 633,
      "EpisodesCount": 12,
      "Status": 0
    }
  },
  {
    "Id": 0,
    "Seasons": [
      "28f834e4-25bb-47e3-a7c7-f9089fbca86f"
    ],
    "Mal": {
      "Id": "40620",
      "Name": "Uramichi Oniisan",
      "ImageUrl": "https://cdn.myanimelist.net/images/anime/1126/115635.webp",
      "MemberCount": 115907,
      "Score": 779,
      "EpisodesCount": 13,
      "Status": 0
    }
  },
  {
    "Id": 0,
    "Seasons": [
      "28f834e4-25bb-47e3-a7c7-f9089fbca86f"
    ],
    "Mal": {
      "Id": "46093",
      "Name": "Shiroi Suna no Aquatope",
      "ImageUrl": "https://cdn.myanimelist.net/images/anime/1932/114952.webp",
      "MemberCount": 115258,
      "Score": 743,
      "EpisodesCount": 24,
      "Status": 0
    }
  },
  {
    "Id": 0,
    "Seasons": [
      "28f834e4-25bb-47e3-a7c7-f9089fbca86f"
    ],
    "Mal": {
      "Id": "42625",
      "Name": "Heion Sedai no Idaten-tachi",
      "ImageUrl": "https://cdn.myanimelist.net/images/anime/1293/115173.webp",
      "MemberCount": 114287,
      "Score": 776,
      "EpisodesCount": 11,
      "Status": 0
    }
  },
  {
    "Id": 0,
    "Seasons": [
      "28f834e4-25bb-47e3-a7c7-f9089fbca86f"
    ],
    "Mal": {
      "Id": "42340",
      "Name": "Meikyuu Black Company",
      "ImageUrl": "https://cdn.myanimelist.net/images/anime/1753/116290.webp",
      "MemberCount": 113612,
      "Score": 737,
      "EpisodesCount": 12,
      "Status": 0
    }
  },
  {
    "Id": 0,
    "Seasons": [
      "28f834e4-25bb-47e3-a7c7-f9089fbca86f"
    ],
    "Mal": {
      "Id": "41812",
      "Name": "Megami-ryou no Ryoubo-kun.",
      "ImageUrl": "https://cdn.myanimelist.net/images/anime/1436/116410.webp",
      "MemberCount": 111095,
      "Score": 658,
      "EpisodesCount": 10,
      "Status": 0
    }
  },
  {
    "Id": 0,
    "Seasons": [
      "28f834e4-25bb-47e3-a7c7-f9089fbca86f"
    ],
    "Mal": {
      "Id": "43814",
      "Name": "Deatte 5-byou de Battle",
      "ImageUrl": "https://cdn.myanimelist.net/images/anime/1145/115565.webp",
      "MemberCount": 106764,
      "Score": 688,
      "EpisodesCount": 12,
      "Status": 0
    }
  },
  {
    "Id": 0,
    "Seasons": [
      "28f834e4-25bb-47e3-a7c7-f9089fbca86f"
    ],
    "Mal": {
      "Id": "42544",
      "Name": "Kaizoku Oujo",
      "ImageUrl": "https://cdn.myanimelist.net/images/anime/1607/117951.webp",
      "MemberCount": 95375,
      "Score": 768,
      "EpisodesCount": 12,
      "Status": 0
    }
  },
  {
    "Id": 0,
    "Seasons": [
      "28f834e4-25bb-47e3-a7c7-f9089fbca86f"
    ],
    "Mal": {
      "Id": "45572",
      "Name": "Mahouka Koukou no Yuutousei",
      "ImageUrl": "https://cdn.myanimelist.net/images/anime/1719/116262.webp",
      "MemberCount": 94296,
      "Score": 656,
      "EpisodesCount": 13,
      "Status": 0
    }
  },
  {
    "Id": 0,
    "Seasons": [
      "28f834e4-25bb-47e3-a7c7-f9089fbca86f"
    ],
    "Mal": {
      "Id": "44881",
      "Name": "100-man no Inochi no Ue ni Ore wa Tatteiru 2nd Season",
      "ImageUrl": "https://cdn.myanimelist.net/images/anime/1424/117718.webp",
      "MemberCount": 91387,
      "Score": 686,
      "EpisodesCount": 12,
      "Status": 0
    }
  },
  {
    "Id": 0,
    "Seasons": [
      "28f834e4-25bb-47e3-a7c7-f9089fbca86f"
    ],
    "Mal": {
      "Id": "40960",
      "Name": "Cheat Kusushi no Slow Life: Isekai ni Tsukurou Drugstore",
      "ImageUrl": "https://cdn.myanimelist.net/images/anime/1787/115817.webp",
      "MemberCount": 82480,
      "Score": 651,
      "EpisodesCount": 12,
      "Status": 0
    }
  },
  {
    "Id": 0,
    "Seasons": [
      "28f834e4-25bb-47e3-a7c7-f9089fbca86f"
    ],
    "Mal": {
      "Id": "48406",
      "Name": "Re-Main",
      "ImageUrl": "https://cdn.myanimelist.net/images/anime/1838/114857.webp",
      "MemberCount": 79633,
      "Score": 726,
      "EpisodesCount": 12,
      "Status": 0
    }
  },
  {
    "Id": 0,
    "Seasons": [
      "28f834e4-25bb-47e3-a7c7-f9089fbca86f"
    ],
    "Mal": {
      "Id": "48488",
      "Name": "Higurashi no Naku Koro ni Sotsu",
      "ImageUrl": "https://cdn.myanimelist.net/images/anime/1083/115046.webp",
      "MemberCount": 72964,
      "Score": 695,
      "EpisodesCount": 15,
      "Status": 0
    }
  },
  {
    "Id": 0,
    "Seasons": [
      "28f834e4-25bb-47e3-a7c7-f9089fbca86f"
    ],
    "Mal": {
      "Id": "48492",
      "Name": "Scarlet Nexus",
      "ImageUrl": "https://cdn.myanimelist.net/images/anime/1314/116004.webp",
      "MemberCount": 61922,
      "Score": 579,
      "EpisodesCount": 26,
      "Status": 0
    }
  },
  {
    "Id": 0,
    "Seasons": [
      "28f834e4-25bb-47e3-a7c7-f9089fbca86f"
    ],
    "Mal": {
      "Id": "43691",
      "Name": "Kageki Shoujo!!",
      "ImageUrl": "https://cdn.myanimelist.net/images/anime/1944/114427.webp",
      "MemberCount": 45750,
      "Score": 786,
      "EpisodesCount": 13,
      "Status": 0
    }
  },
  {
    "Id": 0,
    "Seasons": [
      "28f834e4-25bb-47e3-a7c7-f9089fbca86f"
    ],
    "Mal": {
      "Id": "41530",
      "Name": "Magia Record: Mahou Shoujo Madoka\u2606Magica Gaiden (TV) 2nd Season - Kakusei Zenya",
      "ImageUrl": "https://cdn.myanimelist.net/images/anime/1919/116424.webp",
      "MemberCount": 40927,
      "Score": 708,
      "EpisodesCount": 8,
      "Status": 0
    }
  },
  {
    "Id": 0,
    "Seasons": [
      "28f834e4-25bb-47e3-a7c7-f9089fbca86f"
    ],
    "Mal": {
      "Id": "41169",
      "Name": "Love Live! Superstar!!",
      "ImageUrl": "https://cdn.myanimelist.net/images/anime/1758/115692.webp",
      "MemberCount": 38110,
      "Score": 806,
      "EpisodesCount": 12,
      "Status": 0
    }
  },
  {
    "Id": 0,
    "Seasons": [
      "28f834e4-25bb-47e3-a7c7-f9089fbca86f"
    ],
    "Mal": {
      "Id": "43767",
      "Name": "Night Head 2041",
      "ImageUrl": "https://cdn.myanimelist.net/images/anime/1819/116662.webp",
      "MemberCount": 34987,
      "Score": 664,
      "EpisodesCount": 12,
      "Status": 0
    }
  },
  {
    "Id": 0,
    "Seasons": [
      "28f834e4-25bb-47e3-a7c7-f9089fbca86f"
    ],
    "Mal": {
      "Id": "48470",
      "Name": "D_Cide Traumerei the Animation",
      "ImageUrl": "https://cdn.myanimelist.net/images/anime/1635/117200.webp",
      "MemberCount": 18958,
      "Score": 590,
      "EpisodesCount": 13,
      "Status": 0
    }
  },
  {
    "Id": 0,
    "Seasons": [
      "28f834e4-25bb-47e3-a7c7-f9089fbca86f"
    ],
    "Mal": {
      "Id": "48252",
      "Name": "Ore, Tsushima",
      "ImageUrl": "https://cdn.myanimelist.net/images/anime/1916/112514.webp",
      "MemberCount": 13481,
      "Score": 706,
      "EpisodesCount": 12,
      "Status": 0
    }
  },
  {
    "Id": 0,
    "Seasons": [
      "28f834e4-25bb-47e3-a7c7-f9089fbca86f"
    ],
    "Mal": {
      "Id": "45577",
      "Name": "IDOLiSH7: Third Beat!",
      "ImageUrl": "https://cdn.myanimelist.net/images/anime/1646/115723.webp",
      "MemberCount": 11486,
      "Score": 827,
      "EpisodesCount": 13,
      "Status": 0
    }
  },
  {
    "Id": 0,
    "Seasons": [
      "28f834e4-25bb-47e3-a7c7-f9089fbca86f"
    ],
    "Mal": {
      "Id": "49110",
      "Name": "Yami Shibai 9",
      "ImageUrl": "https://cdn.myanimelist.net/images/anime/1880/115566.webp",
      "MemberCount": 6825,
      "Score": 579,
      "EpisodesCount": 13,
      "Status": 0
    }
  },
  {
    "Id": 0,
    "Seasons": [
      "28f834e4-25bb-47e3-a7c7-f9089fbca86f"
    ],
    "Mal": {
      "Id": "37008",
      "Name": "Tsukipro The Animation 2",
      "ImageUrl": "https://cdn.myanimelist.net/images/anime/1651/116291.webp",
      "MemberCount": 5607,
      "Score": 611,
      "EpisodesCount": 13,
      "Status": 0
    }
  },
  {
    "Id": 0,
    "Seasons": [
      "28f834e4-25bb-47e3-a7c7-f9089fbca86f"
    ],
    "Mal": {
      "Id": "43741",
      "Name": "Getter Robo Arc",
      "ImageUrl": "https://cdn.myanimelist.net/images/anime/1805/116661.webp",
      "MemberCount": 3847,
      "Score": 615,
      "EpisodesCount": 13,
      "Status": 0
    }
  },
  {
    "Id": 0,
    "Seasons": [
      "28f834e4-25bb-47e3-a7c7-f9089fbca86f"
    ],
    "Mal": {
      "Id": "48859",
      "Name": "Pretty All Friends Selection",
      "ImageUrl": "https://cdn.myanimelist.net/images/anime/1968/114657.webp",
      "MemberCount": 1441,
      "Score": 0,
      "EpisodesCount": 16,
      "Status": 0
    }
  },
  {
    "Id": 0,
    "Seasons": [
      "28f834e4-25bb-47e3-a7c7-f9089fbca86f"
    ],
    "Mal": {
      "Id": "21",
      "Name": "One Piece",
      "ImageUrl": "https://cdn.myanimelist.net/images/anime/6/73245.webp",
      "MemberCount": 1663708,
      "Score": 860,
      "EpisodesCount": 0,
      "Status": 0
    }
  },
  {
    "Id": 0,
    "Seasons": [
      "28f834e4-25bb-47e3-a7c7-f9089fbca86f"
    ],
    "Mal": {
      "Id": "41587",
      "Name": "Boku no Hero Academia 5th Season",
      "ImageUrl": "https://cdn.myanimelist.net/images/anime/1911/113611.webp",
      "MemberCount": 734174,
      "Score": 748,
      "EpisodesCount": 25,
      "Status": 0
    }
  },
  {
    "Id": 0,
    "Seasons": [
      "28f834e4-25bb-47e3-a7c7-f9089fbca86f"
    ],
    "Mal": {
      "Id": "42249",
      "Name": "Tokyo Revengers",
      "ImageUrl": "https://cdn.myanimelist.net/images/anime/1884/114790.webp",
      "MemberCount": 672891,
      "Score": 831,
      "EpisodesCount": 24,
      "Status": 0
    }
  },
  {
    "Id": 0,
    "Seasons": [
      "28f834e4-25bb-47e3-a7c7-f9089fbca86f"
    ],
    "Mal": {
      "Id": "34566",
      "Name": "Boruto: Naruto Next Generations",
      "ImageUrl": "https://cdn.myanimelist.net/images/anime/9/84460.webp",
      "MemberCount": 669310,
      "Score": 588,
      "EpisodesCount": 0,
      "Status": 0
    }
  },
  {
    "Id": 0,
    "Seasons": [
      "28f834e4-25bb-47e3-a7c7-f9089fbca86f"
    ],
    "Mal": {
      "Id": "41025",
      "Name": "Fumetsu no Anata e",
      "ImageUrl": "https://cdn.myanimelist.net/images/anime/1880/118484.webp",
      "MemberCount": 556029,
      "Score": 847,
      "EpisodesCount": 20,
      "Status": 0
    }
  },
  {
    "Id": 0,
    "Seasons": [
      "28f834e4-25bb-47e3-a7c7-f9089fbca86f"
    ],
    "Mal": {
      "Id": "235",
      "Name": "Detective Conan",
      "ImageUrl": "https://cdn.myanimelist.net/images/anime/7/75199.webp",
      "MemberCount": 286336,
      "Score": 816,
      "EpisodesCount": 0,
      "Status": 0
    }
  },
  {
    "Id": 0,
    "Seasons": [
      "28f834e4-25bb-47e3-a7c7-f9089fbca86f"
    ],
    "Mal": {
      "Id": "42205",
      "Name": "Shaman King (2021)",
      "ImageUrl": "https://cdn.myanimelist.net/images/anime/1416/113270.webp",
      "MemberCount": 192271,
      "Score": 667,
      "EpisodesCount": 52,
      "Status": 0
    }
  },
  {
    "Id": 0,
    "Seasons": [
      "28f834e4-25bb-47e3-a7c7-f9089fbca86f"
    ],
    "Mal": {
      "Id": "41402",
      "Name": "Mairimashita! Iruma-kun 2nd Season",
      "ImageUrl": "https://cdn.myanimelist.net/images/anime/1527/113656.webp",
      "MemberCount": 172320,
      "Score": 811,
      "EpisodesCount": 21,
      "Status": 0
    }
  },
  {
    "Id": 0,
    "Seasons": [
      "28f834e4-25bb-47e3-a7c7-f9089fbca86f"
    ],
    "Mal": {
      "Id": "42192",
      "Name": "Edens Zero",
      "ImageUrl": "https://cdn.myanimelist.net/images/anime/1011/111811.webp",
      "MemberCount": 149951,
      "Score": 731,
      "EpisodesCount": 25,
      "Status": 0
    }
  },
  {
    "Id": 0,
    "Seasons": [
      "28f834e4-25bb-47e3-a7c7-f9089fbca86f"
    ],
    "Mal": {
      "Id": "966",
      "Name": "Crayon Shin-chan",
      "ImageUrl": "https://cdn.myanimelist.net/images/anime/10/59897.webp",
      "MemberCount": 65959,
      "Score": 772,
      "EpisodesCount": 0,
      "Status": 0
    }
  },
  {
    "Id": 0,
    "Seasons": [
      "28f834e4-25bb-47e3-a7c7-f9089fbca86f"
    ],
    "Mal": {
      "Id": "40682",
      "Name": "Kingdom 3rd Season",
      "ImageUrl": "https://cdn.myanimelist.net/images/anime/1443/111830.webp",
      "MemberCount": 54079,
      "Score": 851,
      "EpisodesCount": 26,
      "Status": 0
    }
  },
  {
    "Id": 0,
    "Seasons": [
      "28f834e4-25bb-47e3-a7c7-f9089fbca86f"
    ],
    "Mal": {
      "Id": "40906",
      "Name": "Dragon Quest: Dai no Daibouken (2020)",
      "ImageUrl": "https://cdn.myanimelist.net/images/anime/1499/109126.webp",
      "MemberCount": 52389,
      "Score": 711,
      "EpisodesCount": 0,
      "Status": 0
    }
  },
  {
    "Id": 0,
    "Seasons": [
      "28f834e4-25bb-47e3-a7c7-f9089fbca86f"
    ],
    "Mal": {
      "Id": "47639",
      "Name": "Blue Reflection Ray",
      "ImageUrl": "https://cdn.myanimelist.net/images/anime/1634/114551.webp",
      "MemberCount": 22202,
      "Score": 576,
      "EpisodesCount": 24,
      "Status": 0
    }
  },
  {
    "Id": 0,
    "Seasons": [
      "28f834e4-25bb-47e3-a7c7-f9089fbca86f"
    ],
    "Mal": {
      "Id": "40145",
      "Name": "Yu\u2606Gi\u2606Oh!: Sevens",
      "ImageUrl": "https://cdn.myanimelist.net/images/anime/1148/106883.webp",
      "MemberCount": 13633,
      "Score": 532,
      "EpisodesCount": 0,
      "Status": 0
    }
  },
  {
    "Id": 0,
    "Seasons": [
      "28f834e4-25bb-47e3-a7c7-f9089fbca86f"
    ],
    "Mal": {
      "Id": "41556",
      "Name": "Maiko-san Chi no Makanai-san",
      "ImageUrl": "https://cdn.myanimelist.net/images/anime/1355/111545.webp",
      "MemberCount": 11142,
      "Score": 664,
      "EpisodesCount": 12,
      "Status": 0
    }
  },
  {
    "Id": 0,
    "Seasons": [
      "28f834e4-25bb-47e3-a7c7-f9089fbca86f"
    ],
    "Mal": {
      "Id": "44191",
      "Name": "Tropical-Rouge! Precure",
      "ImageUrl": "https://cdn.myanimelist.net/images/anime/1184/110907.webp",
      "MemberCount": 6880,
      "Score": 714,
      "EpisodesCount": 0,
      "Status": 0
    }
  },
  {
    "Id": 0,
    "Seasons": [
      "28f834e4-25bb-47e3-a7c7-f9089fbca86f"
    ],
    "Mal": {
      "Id": "2406",
      "Name": "Sazae-san",
      "ImageUrl": "https://cdn.myanimelist.net/images/anime/9/25502.webp",
      "MemberCount": 6484,
      "Score": 611,
      "EpisodesCount": 0,
      "Status": 0
    }
  },
  {
    "Id": 0,
    "Seasons": [
      "28f834e4-25bb-47e3-a7c7-f9089fbca86f"
    ],
    "Mal": {
      "Id": "44056",
      "Name": "Tokyo Gambo",
      "ImageUrl": "https://cdn.myanimelist.net/images/anime/1758/110280.webp",
      "MemberCount": 2875,
      "Score": 0,
      "EpisodesCount": 0,
      "Status": 0
    }
  },
  {
    "Id": 0,
    "Seasons": [
      "28f834e4-25bb-47e3-a7c7-f9089fbca86f"
    ],
    "Mal": {
      "Id": "32353",
      "Name": "Bonobono (TV 2016)",
      "ImageUrl": "https://cdn.myanimelist.net/images/anime/13/77617.webp",
      "MemberCount": 2523,
      "Score": 639,
      "EpisodesCount": 0,
      "Status": 0
    }
  },
  {
    "Id": 0,
    "Seasons": [
      "28f834e4-25bb-47e3-a7c7-f9089fbca86f"
    ],
    "Mal": {
      "Id": "45618",
      "Name": "Dinosaur Biyori",
      "ImageUrl": "https://cdn.myanimelist.net/images/anime/1382/116139.webp",
      "MemberCount": 1725,
      "Score": 0,
      "EpisodesCount": 26,
      "Status": 0
    }
  },
  {
    "Id": 0,
    "Seasons": [
      "28f834e4-25bb-47e3-a7c7-f9089fbca86f"
    ],
    "Mal": {
      "Id": "48442",
      "Name": "Shikaru Neko",
      "ImageUrl": "https://cdn.myanimelist.net/images/anime/1008/113384.webp",
      "MemberCount": 1212,
      "Score": 0,
      "EpisodesCount": 0,
      "Status": 0
    }
  },
  {
    "Id": 0,
    "Seasons": [
      "28f834e4-25bb-47e3-a7c7-f9089fbca86f"
    ],
    "Mal": {
      "Id": "48391",
      "Name": "Mazica Party",
      "ImageUrl": "https://cdn.myanimelist.net/images/anime/1740/113501.webp",
      "MemberCount": 1115,
      "Score": 538,
      "EpisodesCount": 0,
      "Status": 0
    }
  },
  {
    "Id": 0,
    "Seasons": [
      "28f834e4-25bb-47e3-a7c7-f9089fbca86f"
    ],
    "Mal": {
      "Id": "33398",
      "Name": "Neko Konogoro",
      "ImageUrl": "https://cdn.myanimelist.net/images/anime/1877/91297.webp",
      "MemberCount": 1087,
      "Score": 0,
      "EpisodesCount": 0,
      "Status": 0
    }
  },
  {
    "Id": 0,
    "Seasons": [
      "28f834e4-25bb-47e3-a7c7-f9089fbca86f"
    ],
    "Mal": {
      "Id": "35478",
      "Name": "Neko no Robu",
      "ImageUrl": "https://cdn.myanimelist.net/images/anime/1859/91295.webp",
      "MemberCount": 1064,
      "Score": 0,
      "EpisodesCount": 0,
      "Status": 0
    }
  },
  {
    "Id": 0,
    "Seasons": [
      "28f834e4-25bb-47e3-a7c7-f9089fbca86f"
    ],
    "Mal": {
      "Id": "45207",
      "Name": "Okashi na Sabaku no Suna to Manu",
      "ImageUrl": "https://cdn.myanimelist.net/images/anime/1208/111257.webp",
      "MemberCount": 1053,
      "Score": 0,
      "EpisodesCount": 50,
      "Status": 0
    }
  },
  {
    "Id": 0,
    "Seasons": [
      "28f834e4-25bb-47e3-a7c7-f9089fbca86f"
    ],
    "Mal": {
      "Id": "42482",
      "Name": "Seizei Ganbare! Mahou Shoujo Kurumi 3rd Season",
      "ImageUrl": "https://cdn.myanimelist.net/images/anime/1097/108552.webp",
      "MemberCount": 865,
      "Score": 0,
      "EpisodesCount": 25,
      "Status": 0
    }
  },
  {
    "Id": 0,
    "Seasons": [
      "28f834e4-25bb-47e3-a7c7-f9089fbca86f"
    ],
    "Mal": {
      "Id": "30151",
      "Name": "Kamiusagi Rope: Warau Asa ni wa Fukuraitaru tte Maji ssuka!?",
      "ImageUrl": "https://cdn.myanimelist.net/images/anime/6/72182.webp",
      "MemberCount": 804,
      "Score": 0,
      "EpisodesCount": 0,
      "Status": 0
    }
  },
  {
    "Id": 0,
    "Seasons": [
      "28f834e4-25bb-47e3-a7c7-f9089fbca86f"
    ],
    "Mal": {
      "Id": "10506",
      "Name": "Shiawase Haitatsu Taneko",
      "ImageUrl": "https://cdn.myanimelist.net/images/anime/2/28900.webp",
      "MemberCount": 578,
      "Score": 0,
      "EpisodesCount": 0,
      "Status": 0
    }
  },
  {
    "Id": 0,
    "Seasons": [
      "28f834e4-25bb-47e3-a7c7-f9089fbca86f"
    ],
    "Mal": {
      "Id": "42870",
      "Name": "Uchuu Nanchara Kotetsu-kun",
      "ImageUrl": "https://cdn.myanimelist.net/images/anime/1226/112286.webp",
      "MemberCount": 491,
      "Score": 0,
      "EpisodesCount": 0,
      "Status": 0
    }
  },
  {
    "Id": 0,
    "Seasons": [
      "28f834e4-25bb-47e3-a7c7-f9089fbca86f"
    ],
    "Mal": {
      "Id": "35694",
      "Name": "Kirin the Noop",
      "ImageUrl": "https://cdn.myanimelist.net/images/anime/13/86110.webp",
      "MemberCount": 392,
      "Score": 0,
      "EpisodesCount": 0,
      "Status": 0
    }
  },
  {
    "Id": 0,
    "Seasons": [
      "28f834e4-25bb-47e3-a7c7-f9089fbca86f"
    ],
    "Mal": {
      "Id": "43416",
      "Name": "Kaoru no Taisetsu na Mono",
      "ImageUrl": "https://cdn.myanimelist.net/images/anime/1352/109736.webp",
      "MemberCount": 360,
      "Score": 0,
      "EpisodesCount": 0,
      "Status": 0
    }
  },
  {
    "Id": 0,
    "Seasons": [
      "28f834e4-25bb-47e3-a7c7-f9089fbca86f"
    ],
    "Mal": {
      "Id": "42068",
      "Name": "Utau Soccer Panda Mifanda",
      "ImageUrl": "https://cdn.myanimelist.net/images/anime/1296/108533.webp",
      "MemberCount": 331,
      "Score": 0,
      "EpisodesCount": 12,
      "Status": 0
    }
  },
  {
    "Id": 0,
    "Seasons": [
      "28f834e4-25bb-47e3-a7c7-f9089fbca86f"
    ],
    "Mal": {
      "Id": "38776",
      "Name": "Manul no Yuube",
      "ImageUrl": "https://cdn.myanimelist.net/images/anime/1980/96936.webp",
      "MemberCount": 319,
      "Score": 0,
      "EpisodesCount": 0,
      "Status": 0
    }
  },
  {
    "Id": 0,
    "Seasons": [
      "28f834e4-25bb-47e3-a7c7-f9089fbca86f"
    ],
    "Mal": {
      "Id": "49357",
      "Name": "Star Wars: Visions",
      "ImageUrl": "https://cdn.myanimelist.net/images/anime/1958/117686.webp",
      "MemberCount": 43761,
      "Score": 737,
      "EpisodesCount": 9,
      "Status": 0
    }
  },
  {
    "Id": 0,
    "Seasons": [
      "28f834e4-25bb-47e3-a7c7-f9089fbca86f"
    ],
    "Mal": {
      "Id": "40434",
      "Name": "Mo Dao Zu Shi: Wanjie Pian",
      "ImageUrl": "https://cdn.myanimelist.net/images/anime/1634/116782.webp",
      "MemberCount": 38388,
      "Score": 866,
      "EpisodesCount": 12,
      "Status": 0
    }
  },
  {
    "Id": 0,
    "Seasons": [
      "28f834e4-25bb-47e3-a7c7-f9089fbca86f"
    ],
    "Mal": {
      "Id": "49605",
      "Name": "Ganbare Douki-chan",
      "ImageUrl": "https://cdn.myanimelist.net/images/anime/1185/117548.webp",
      "MemberCount": 31397,
      "Score": 681,
      "EpisodesCount": 12,
      "Status": 0
    }
  },
  {
    "Id": 0,
    "Seasons": [
      "28f834e4-25bb-47e3-a7c7-f9089fbca86f"
    ],
    "Mal": {
      "Id": "42940",
      "Name": "Hanma Baki: Son of Ogre",
      "ImageUrl": "https://cdn.myanimelist.net/images/anime/1072/116472.webp",
      "MemberCount": 29240,
      "Score": 759,
      "EpisodesCount": 12,
      "Status": 0
    }
  },
  {
    "Id": 0,
    "Seasons": [
      "28f834e4-25bb-47e3-a7c7-f9089fbca86f"
    ],
    "Mal": {
      "Id": "48641",
      "Name": "Obey Me!",
      "ImageUrl": "https://cdn.myanimelist.net/images/anime/1416/113986.webp",
      "MemberCount": 23724,
      "Score": 755,
      "EpisodesCount": 0,
      "Status": 0
    }
  },
  {
    "Id": 0,
    "Seasons": [
      "28f834e4-25bb-47e3-a7c7-f9089fbca86f"
    ],
    "Mal": {
      "Id": "49854",
      "Name": "Getsuyoubi no Tawawa 2",
      "ImageUrl": "https://cdn.myanimelist.net/images/anime/1370/117813.webp",
      "MemberCount": 19059,
      "Score": 688,
      "EpisodesCount": 12,
      "Status": 0
    }
  },
  {
    "Id": 0,
    "Seasons": [
      "28f834e4-25bb-47e3-a7c7-f9089fbca86f"
    ],
    "Mal": {
      "Id": "42976",
      "Name": "Biohazard: Infinite Darkness",
      "ImageUrl": "https://cdn.myanimelist.net/images/anime/1662/116785.webp",
      "MemberCount": 10181,
      "Score": 625,
      "EpisodesCount": 4,
      "Status": 0
    }
  },
  {
    "Id": 0,
    "Seasons": [
      "28f834e4-25bb-47e3-a7c7-f9089fbca86f"
    ],
    "Mal": {
      "Id": "48941",
      "Name": "Quanzhi Fashi V",
      "ImageUrl": "https://cdn.myanimelist.net/images/anime/1974/114887.webp",
      "MemberCount": 8957,
      "Score": 733,
      "EpisodesCount": 12,
      "Status": 0
    }
  },
  {
    "Id": 0,
    "Seasons": [
      "28f834e4-25bb-47e3-a7c7-f9089fbca86f"
    ],
    "Mal": {
      "Id": "49915",
      "Name": "Hitori no Shita: The Outcast 4th Season",
      "ImageUrl": "https://cdn.myanimelist.net/images/anime/1539/117964.webp",
      "MemberCount": 3470,
      "Score": 0,
      "EpisodesCount": 12,
      "Status": 0
    }
  },
  {
    "Id": 0,
    "Seasons": [
      "28f834e4-25bb-47e3-a7c7-f9089fbca86f"
    ],
    "Mal": {
      "Id": "45961",
      "Name": "Assault Lily: Fruits",
      "ImageUrl": "https://cdn.myanimelist.net/images/anime/1444/116888.webp",
      "MemberCount": 2977,
      "Score": 618,
      "EpisodesCount": 0,
      "Status": 0
    }
  },
  {
    "Id": 0,
    "Seasons": [
      "28f834e4-25bb-47e3-a7c7-f9089fbca86f"
    ],
    "Mal": {
      "Id": "49507",
      "Name": "Shuumatsu no Walk\u00FCre Mini Anime",
      "ImageUrl": "https://cdn.myanimelist.net/images/anime/1899/116794.webp",
      "MemberCount": 2976,
      "Score": 613,
      "EpisodesCount": 0,
      "Status": 0
    }
  },
  {
    "Id": 0,
    "Seasons": [
      "28f834e4-25bb-47e3-a7c7-f9089fbca86f"
    ],
    "Mal": {
      "Id": "49410",
      "Name": "Shiroi Suna no Aquatope Mini",
      "ImageUrl": "https://cdn.myanimelist.net/images/anime/1747/116566.webp",
      "MemberCount": 2635,
      "Score": 634,
      "EpisodesCount": 0,
      "Status": 0
    }
  },
  {
    "Id": 0,
    "Seasons": [
      "28f834e4-25bb-47e3-a7c7-f9089fbca86f"
    ],
    "Mal": {
      "Id": "48892",
      "Name": "Yoshimaho",
      "ImageUrl": "https://cdn.myanimelist.net/images/anime/1962/114761.webp",
      "MemberCount": 2265,
      "Score": 0,
      "EpisodesCount": 0,
      "Status": 0
    }
  },
  {
    "Id": 0,
    "Seasons": [
      "28f834e4-25bb-47e3-a7c7-f9089fbca86f"
    ],
    "Mal": {
      "Id": "49204",
      "Name": "Yuan Shen Haojie",
      "ImageUrl": "https://cdn.myanimelist.net/images/anime/1015/115808.webp",
      "MemberCount": 2174,
      "Score": 0,
      "EpisodesCount": 52,
      "Status": 0
    }
  },
  {
    "Id": 0,
    "Seasons": [
      "28f834e4-25bb-47e3-a7c7-f9089fbca86f"
    ],
    "Mal": {
      "Id": "49392",
      "Name": "Ore, Tsushima (ONA)",
      "ImageUrl": "https://cdn.myanimelist.net/images/anime/1809/117254.webp",
      "MemberCount": 2145,
      "Score": 644,
      "EpisodesCount": 0,
      "Status": 0
    }
  },
  {
    "Id": 0,
    "Seasons": [
      "28f834e4-25bb-47e3-a7c7-f9089fbca86f"
    ],
    "Mal": {
      "Id": "48962",
      "Name": "Xie Wang Zhui Qi 3: Shen Nu Guilai",
      "ImageUrl": "https://cdn.myanimelist.net/images/anime/1108/114927.webp",
      "MemberCount": 1849,
      "Score": 0,
      "EpisodesCount": 0,
      "Status": 0
    }
  },
  {
    "Id": 0,
    "Seasons": [
      "28f834e4-25bb-47e3-a7c7-f9089fbca86f"
    ],
    "Mal": {
      "Id": "44067",
      "Name": "Bai Yao Pu 2nd Season",
      "ImageUrl": "https://cdn.myanimelist.net/images/anime/1898/115957.webp",
      "MemberCount": 1624,
      "Score": 685,
      "EpisodesCount": 12,
      "Status": 0
    }
  },
  {
    "Id": 0,
    "Seasons": [
      "28f834e4-25bb-47e3-a7c7-f9089fbca86f"
    ],
    "Mal": {
      "Id": "49638",
      "Name": "Douluo Dalu: Chongfan Haotian",
      "ImageUrl": "https://cdn.myanimelist.net/images/anime/1269/117301.webp",
      "MemberCount": 1483,
      "Score": 774,
      "EpisodesCount": 13,
      "Status": 0
    }
  },
  {
    "Id": 0,
    "Seasons": [
      "28f834e4-25bb-47e3-a7c7-f9089fbca86f"
    ],
    "Mal": {
      "Id": "40885",
      "Name": "Can Ci Pin: Fangzhu Xingkong",
      "ImageUrl": "https://cdn.myanimelist.net/images/anime/1650/116012.webp",
      "MemberCount": 1428,
      "Score": 642,
      "EpisodesCount": 16,
      "Status": 0
    }
  },
  {
    "Id": 0,
    "Seasons": [
      "28f834e4-25bb-47e3-a7c7-f9089fbca86f"
    ],
    "Mal": {
      "Id": "49652",
      "Name": "Shiguang Dailiren Specials",
      "ImageUrl": "https://cdn.myanimelist.net/images/anime/1914/117361.webp",
      "MemberCount": 1421,
      "Score": 584,
      "EpisodesCount": 0,
      "Status": 0
    }
  },
  {
    "Id": 0,
    "Seasons": [
      "28f834e4-25bb-47e3-a7c7-f9089fbca86f"
    ],
    "Mal": {
      "Id": "44065",
      "Name": "Dinghai Fusheng Lu",
      "ImageUrl": "https://cdn.myanimelist.net/images/anime/1943/115892.webp",
      "MemberCount": 1134,
      "Score": 0,
      "EpisodesCount": 12,
      "Status": 0
    }
  },
  {
    "Id": 0,
    "Seasons": [
      "28f834e4-25bb-47e3-a7c7-f9089fbca86f"
    ],
    "Mal": {
      "Id": "44071",
      "Name": "Yuan Long 2nd Season",
      "ImageUrl": "https://cdn.myanimelist.net/images/anime/1138/110307.webp",
      "MemberCount": 1092,
      "Score": 687,
      "EpisodesCount": 16,
      "Status": 0
    }
  },
  {
    "Id": 0,
    "Seasons": [
      "28f834e4-25bb-47e3-a7c7-f9089fbca86f"
    ],
    "Mal": {
      "Id": "48875",
      "Name": "Dahuoji Yu Gongzhu Qun",
      "ImageUrl": "https://cdn.myanimelist.net/images/anime/1951/114703.webp",
      "MemberCount": 1083,
      "Score": 0,
      "EpisodesCount": 0,
      "Status": 0
    }
  },
  {
    "Id": 0,
    "Seasons": [
      "28f834e4-25bb-47e3-a7c7-f9089fbca86f"
    ],
    "Mal": {
      "Id": "49860",
      "Name": "Umisea",
      "ImageUrl": "https://cdn.myanimelist.net/images/anime/1910/117800.webp",
      "MemberCount": 955,
      "Score": 671,
      "EpisodesCount": 4,
      "Status": 0
    }
  },
  {
    "Id": 0,
    "Seasons": [
      "28f834e4-25bb-47e3-a7c7-f9089fbca86f"
    ],
    "Mal": {
      "Id": "49208",
      "Name": "Heibai Wushuang 3rd Season",
      "ImageUrl": "https://cdn.myanimelist.net/images/anime/1604/115814.webp",
      "MemberCount": 927,
      "Score": 0,
      "EpisodesCount": 12,
      "Status": 0
    }
  },
  {
    "Id": 0,
    "Seasons": [
      "28f834e4-25bb-47e3-a7c7-f9089fbca86f"
    ],
    "Mal": {
      "Id": "48177",
      "Name": "Ichiban Chikakute Tooi Hoshi",
      "ImageUrl": "https://cdn.myanimelist.net/images/anime/1388/112416.webp",
      "MemberCount": 762,
      "Score": 604,
      "EpisodesCount": 1,
      "Status": 0
    }
  },
  {
    "Id": 0,
    "Seasons": [
      "28f834e4-25bb-47e3-a7c7-f9089fbca86f"
    ],
    "Mal": {
      "Id": "49895",
      "Name": "Go! Saitama",
      "ImageUrl": "https://cdn.myanimelist.net/images/anime/1893/117904.webp",
      "MemberCount": 704,
      "Score": 698,
      "EpisodesCount": 1,
      "Status": 0
    }
  },
  {
    "Id": 0,
    "Seasons": [
      "28f834e4-25bb-47e3-a7c7-f9089fbca86f"
    ],
    "Mal": {
      "Id": "40732",
      "Name": "Shaonian Ge Xing: Feng Hua Xue Yue Pian",
      "ImageUrl": "https://cdn.myanimelist.net/images/anime/1777/110315.webp",
      "MemberCount": 694,
      "Score": 0,
      "EpisodesCount": 32,
      "Status": 0
    }
  },
  {
    "Id": 0,
    "Seasons": [
      "28f834e4-25bb-47e3-a7c7-f9089fbca86f"
    ],
    "Mal": {
      "Id": "49982",
      "Name": "Geu Yeoreum",
      "ImageUrl": "https://cdn.myanimelist.net/images/anime/1431/118423.webp",
      "MemberCount": 687,
      "Score": 0,
      "EpisodesCount": 7,
      "Status": 0
    }
  },
  {
    "Id": 0,
    "Seasons": [
      "28f834e4-25bb-47e3-a7c7-f9089fbca86f"
    ],
    "Mal": {
      "Id": "49386",
      "Name": "Xingchen Bian: Xichen Yao Hai",
      "ImageUrl": "https://cdn.myanimelist.net/images/anime/1676/117014.webp",
      "MemberCount": 636,
      "Score": 0,
      "EpisodesCount": 12,
      "Status": 0
    }
  },
  {
    "Id": 0,
    "Seasons": [
      "28f834e4-25bb-47e3-a7c7-f9089fbca86f"
    ],
    "Mal": {
      "Id": "49398",
      "Name": "Wu Geng Ji 4th Season",
      "ImageUrl": "https://cdn.myanimelist.net/images/anime/1875/116414.webp",
      "MemberCount": 557,
      "Score": 0,
      "EpisodesCount": 42,
      "Status": 0
    }
  },
  {
    "Id": 0,
    "Seasons": [
      "28f834e4-25bb-47e3-a7c7-f9089fbca86f"
    ],
    "Mal": {
      "Id": "44411",
      "Name": "Shi Ye Miao Yin",
      "ImageUrl": "https://cdn.myanimelist.net/images/anime/1429/110608.webp",
      "MemberCount": 491,
      "Score": 0,
      "EpisodesCount": 11,
      "Status": 0
    }
  },
  {
    "Id": 0,
    "Seasons": [
      "28f834e4-25bb-47e3-a7c7-f9089fbca86f"
    ],
    "Mal": {
      "Id": "44075",
      "Name": "Sou Xuan Lu Zhi Chen Ling Ji",
      "ImageUrl": "https://cdn.myanimelist.net/images/anime/1674/110313.webp",
      "MemberCount": 437,
      "Score": 0,
      "EpisodesCount": 6,
      "Status": 0
    }
  },
  {
    "Id": 0,
    "Seasons": [
      "28f834e4-25bb-47e3-a7c7-f9089fbca86f"
    ],
    "Mal": {
      "Id": "49448",
      "Name": "Ni Tian Zhizun",
      "ImageUrl": "https://cdn.myanimelist.net/images/anime/1557/117031.webp",
      "MemberCount": 323,
      "Score": 0,
      "EpisodesCount": 60,
      "Status": 0
    }
  },
  {
    "Id": 0,
    "Seasons": [
      "28f834e4-25bb-47e3-a7c7-f9089fbca86f"
    ],
    "Mal": {
      "Id": "49370",
      "Name": "Mini Van Large",
      "ImageUrl": "https://cdn.myanimelist.net/images/anime/1758/116411.webp",
      "MemberCount": 309,
      "Score": 0,
      "EpisodesCount": 0,
      "Status": 0
    }
  },
  {
    "Id": 0,
    "Seasons": [
      "28f834e4-25bb-47e3-a7c7-f9089fbca86f"
    ],
    "Mal": {
      "Id": "49633",
      "Name": "Fate/kaleid liner Prisma\u2606Illya Movie: Licht - Namae no Nai Shoujo Mini Anime",
      "ImageUrl": "https://cdn.myanimelist.net/images/anime/1647/117279.webp",
      "MemberCount": 295,
      "Score": 0,
      "EpisodesCount": 3,
      "Status": 0
    }
  },
  {
    "Id": 0,
    "Seasons": [
      "28f834e4-25bb-47e3-a7c7-f9089fbca86f"
    ],
    "Mal": {
      "Id": "49284",
      "Name": "Shabake",
      "ImageUrl": "https://cdn.myanimelist.net/images/anime/1782/116029.webp",
      "MemberCount": 269,
      "Score": 0,
      "EpisodesCount": 1,
      "Status": 0
    }
  },
  {
    "Id": 0,
    "Seasons": [
      "28f834e4-25bb-47e3-a7c7-f9089fbca86f"
    ],
    "Mal": {
      "Id": "48000",
      "Name": "Xian Yu Ge",
      "ImageUrl": "https://cdn.myanimelist.net/images/anime/1785/116014.webp",
      "MemberCount": 237,
      "Score": 0,
      "EpisodesCount": 0,
      "Status": 0
    }
  },
  {
    "Id": 0,
    "Seasons": [
      "28f834e4-25bb-47e3-a7c7-f9089fbca86f"
    ],
    "Mal": {
      "Id": "49718",
      "Name": "Huyao Xiao Hongniang: Yue Hong 2",
      "ImageUrl": "https://cdn.myanimelist.net/images/anime/1933/118633.webp",
      "MemberCount": 167,
      "Score": 0,
      "EpisodesCount": 1,
      "Status": 0
    }
  },
  {
    "Id": 0,
    "Seasons": [
      "28f834e4-25bb-47e3-a7c7-f9089fbca86f"
    ],
    "Mal": {
      "Id": "49454",
      "Name": "Gabuli",
      "ImageUrl": "https://cdn.myanimelist.net/images/anime/1499/116618.webp",
      "MemberCount": 124,
      "Score": 0,
      "EpisodesCount": 0,
      "Status": 0
    }
  },
  {
    "Id": 0,
    "Seasons": [
      "28f834e4-25bb-47e3-a7c7-f9089fbca86f"
    ],
    "Mal": {
      "Id": "49433",
      "Name": "Youxia Zhanji",
      "ImageUrl": "https://cdn.myanimelist.net/images/anime/1616/116551.webp",
      "MemberCount": 121,
      "Score": 0,
      "EpisodesCount": 20,
      "Status": 0
    }
  },
  {
    "Id": 0,
    "Seasons": [
      "28f834e4-25bb-47e3-a7c7-f9089fbca86f"
    ],
    "Mal": {
      "Id": "49873",
      "Name": "Jiu Tian Xuan Di Jue",
      "ImageUrl": "https://cdn.myanimelist.net/images/anime/1880/117911.webp",
      "MemberCount": 115,
      "Score": 0,
      "EpisodesCount": 40,
      "Status": 0
    }
  },
  {
    "Id": 0,
    "Seasons": [
      "28f834e4-25bb-47e3-a7c7-f9089fbca86f"
    ],
    "Mal": {
      "Id": "49275",
      "Name": "Renou Xueyuan",
      "ImageUrl": "https://cdn.myanimelist.net/images/anime/1506/116008.webp",
      "MemberCount": 101,
      "Score": 0,
      "EpisodesCount": 10,
      "Status": 0
    }
  },
  {
    "Id": 0,
    "Seasons": [
      "28f834e4-25bb-47e3-a7c7-f9089fbca86f"
    ],
    "Mal": {
      "Id": "49952",
      "Name": "Wo Qi Ku Liao Baiwan Xiulian Zhe",
      "ImageUrl": "https://cdn.myanimelist.net/images/anime/1556/118167.webp",
      "MemberCount": 96,
      "Score": 0,
      "EpisodesCount": 60,
      "Status": 0
    }
  },
  {
    "Id": 0,
    "Seasons": [
      "28f834e4-25bb-47e3-a7c7-f9089fbca86f"
    ],
    "Mal": {
      "Id": "49708",
      "Name": "Shaman King (2021): Funbari Onsen Hanjouki",
      "ImageUrl": "https://cdn.myanimelist.net/images/anime/1679/117975.webp",
      "MemberCount": 86,
      "Score": 0,
      "EpisodesCount": 0,
      "Status": 0
    }
  },
  {
    "Id": 0,
    "Seasons": [
      "28f834e4-25bb-47e3-a7c7-f9089fbca86f"
    ],
    "Mal": {
      "Id": "49941",
      "Name": "Gundam UC x Nike SB",
      "ImageUrl": "https://cdn.myanimelist.net/images/anime/1088/118083.webp",
      "MemberCount": 80,
      "Score": 0,
      "EpisodesCount": 1,
      "Status": 0
    }
  },
  {
    "Id": 0,
    "Seasons": [
      "28f834e4-25bb-47e3-a7c7-f9089fbca86f"
    ],
    "Mal": {
      "Id": "49276",
      "Name": "Mao Ling Xiangce",
      "ImageUrl": "https://cdn.myanimelist.net/images/anime/1277/116010.webp",
      "MemberCount": 73,
      "Score": 0,
      "EpisodesCount": 0,
      "Status": 0
    }
  },
  {
    "Id": 0,
    "Seasons": [
      "28f834e4-25bb-47e3-a7c7-f9089fbca86f"
    ],
    "Mal": {
      "Id": "49794",
      "Name": "Yan Wang: Guai Hualang",
      "ImageUrl": "https://cdn.myanimelist.net/images/anime/1545/117655.webp",
      "MemberCount": 67,
      "Score": 0,
      "EpisodesCount": 12,
      "Status": 0
    }
  },
  {
    "Id": 0,
    "Seasons": [
      "28f834e4-25bb-47e3-a7c7-f9089fbca86f"
    ],
    "Mal": {
      "Id": "49445",
      "Name": "Tora to Mike",
      "ImageUrl": "https://cdn.myanimelist.net/images/anime/1718/117571.webp",
      "MemberCount": 59,
      "Score": 0,
      "EpisodesCount": 24,
      "Status": 0
    }
  },
  {
    "Id": 0,
    "Seasons": [
      "28f834e4-25bb-47e3-a7c7-f9089fbca86f"
    ],
    "Mal": {
      "Id": "49355",
      "Name": "Ling Yun Daima",
      "ImageUrl": "https://cdn.myanimelist.net/images/anime/1835/116315.webp",
      "MemberCount": 54,
      "Score": 0,
      "EpisodesCount": 20,
      "Status": 0
    }
  },
  {
    "Id": 0,
    "Seasons": [
      "28f834e4-25bb-47e3-a7c7-f9089fbca86f"
    ],
    "Mal": {
      "Id": "49841",
      "Name": "Chun Qiu Feng Shen",
      "ImageUrl": "https://cdn.myanimelist.net/images/anime/1126/117822.webp",
      "MemberCount": 52,
      "Score": 0,
      "EpisodesCount": 24,
      "Status": 0
    }
  },
  {
    "Id": 0,
    "Seasons": [
      "28f834e4-25bb-47e3-a7c7-f9089fbca86f"
    ],
    "Mal": {
      "Id": "49867",
      "Name": "Budo Xianzun",
      "ImageUrl": "https://cdn.myanimelist.net/images/qm_50.gif",
      "MemberCount": 45,
      "Score": 0,
      "EpisodesCount": 0,
      "Status": 0
    }
  },
  {
    "Id": 0,
    "Seasons": [
      "28f834e4-25bb-47e3-a7c7-f9089fbca86f"
    ],
    "Mal": {
      "Id": "49205",
      "Name": "Hong Huang",
      "ImageUrl": "https://cdn.myanimelist.net/images/anime/1512/115811.webp",
      "MemberCount": 45,
      "Score": 0,
      "EpisodesCount": 13,
      "Status": 0
    }
  },
  {
    "Id": 0,
    "Seasons": [
      "28f834e4-25bb-47e3-a7c7-f9089fbca86f"
    ],
    "Mal": {
      "Id": "49277",
      "Name": "Jiu Jiu Ba Shi Yi",
      "ImageUrl": "https://cdn.myanimelist.net/images/anime/1359/116011.webp",
      "MemberCount": 39,
      "Score": 0,
      "EpisodesCount": 12,
      "Status": 0
    }
  },
  {
    "Id": 0,
    "Seasons": [
      "28f834e4-25bb-47e3-a7c7-f9089fbca86f"
    ],
    "Mal": {
      "Id": "49354",
      "Name": "Ankoku Kazoku Warabi-san",
      "ImageUrl": "https://cdn.myanimelist.net/images/anime/1724/116314.webp",
      "MemberCount": 33,
      "Score": 0,
      "EpisodesCount": 20,
      "Status": 0
    }
  },
  {
    "Id": 0,
    "Seasons": [
      "28f834e4-25bb-47e3-a7c7-f9089fbca86f"
    ],
    "Mal": {
      "Id": "49668",
      "Name": "\u0022Hataraku\u0022 no 100-nenshi",
      "ImageUrl": "https://cdn.myanimelist.net/images/anime/1803/117355.webp",
      "MemberCount": 30,
      "Score": 0,
      "EpisodesCount": 1,
      "Status": 0
    }
  },
  {
    "Id": 0,
    "Seasons": [
      "28f834e4-25bb-47e3-a7c7-f9089fbca86f"
    ],
    "Mal": {
      "Id": "49771",
      "Name": "Fire Emblem Heroes: Part 2 - Mini Chara Theater",
      "ImageUrl": "https://cdn.myanimelist.net/images/anime/1247/117557.webp",
      "MemberCount": 0,
      "Score": 0,
      "EpisodesCount": 1,
      "Status": 0
    }
  },
  {
    "Id": 0,
    "Seasons": [
      "28f834e4-25bb-47e3-a7c7-f9089fbca86f"
    ],
    "Mal": {
      "Id": "44931",
      "Name": "Tonikaku Kawaii: SNS",
      "ImageUrl": "https://cdn.myanimelist.net/images/anime/1773/116805.webp",
      "MemberCount": 80679,
      "Score": 814,
      "EpisodesCount": 1,
      "Status": 0
    }
  },
  {
    "Id": 0,
    "Seasons": [
      "28f834e4-25bb-47e3-a7c7-f9089fbca86f"
    ],
    "Mal": {
      "Id": "48438",
      "Name": "Mahoutsukai no Yome: Nishi no Shounen to Seiran no Kishi",
      "ImageUrl": "https://cdn.myanimelist.net/images/anime/1454/117626.webp",
      "MemberCount": 37556,
      "Score": 760,
      "EpisodesCount": 3,
      "Status": 0
    }
  },
  {
    "Id": 0,
    "Seasons": [
      "28f834e4-25bb-47e3-a7c7-f9089fbca86f"
    ],
    "Mal": {
      "Id": "49457",
      "Name": "Otome Game no Hametsu Flag shika Nai Akuyaku Reijou ni Tensei shiteshimatta... OVA",
      "ImageUrl": "https://cdn.myanimelist.net/images/anime/1175/116614.webp",
      "MemberCount": 11691,
      "Score": 658,
      "EpisodesCount": 1,
      "Status": 0
    }
  },
  {
    "Id": 0,
    "Seasons": [
      "28f834e4-25bb-47e3-a7c7-f9089fbca86f"
    ],
    "Mal": {
      "Id": "43506",
      "Name": "Alice Gear Aegis: Doki! Actress Darake no Mermaid Grand Prix\u2665",
      "ImageUrl": "https://cdn.myanimelist.net/images/anime/1039/116828.webp",
      "MemberCount": 605,
      "Score": 0,
      "EpisodesCount": 1,
      "Status": 0
    }
  },
  {
    "Id": 0,
    "Seasons": [
      "28f834e4-25bb-47e3-a7c7-f9089fbca86f"
    ],
    "Mal": {
      "Id": "39175",
      "Name": "Cider no You ni Kotoba ga Wakiagaru",
      "ImageUrl": "https://cdn.myanimelist.net/images/anime/1952/116031.webp",
      "MemberCount": 104169,
      "Score": 751,
      "EpisodesCount": 1,
      "Status": 0
    }
  },
  {
    "Id": 0,
    "Seasons": [
      "28f834e4-25bb-47e3-a7c7-f9089fbca86f"
    ],
    "Mal": {
      "Id": "44200",
      "Name": "Boku no Hero Academia the Movie 3: World Heroes\u0027 Mission",
      "ImageUrl": "https://cdn.myanimelist.net/images/anime/1049/115605.webp",
      "MemberCount": 103408,
      "Score": 762,
      "EpisodesCount": 1,
      "Status": 0
    }
  },
  {
    "Id": 0,
    "Seasons": [
      "28f834e4-25bb-47e3-a7c7-f9089fbca86f"
    ],
    "Mal": {
      "Id": "38400",
      "Name": "Free! Movie 4: The Final Stroke",
      "ImageUrl": "https://cdn.myanimelist.net/images/anime/1450/117893.webp",
      "MemberCount": 43514,
      "Score": 697,
      "EpisodesCount": 1,
      "Status": 0
    }
  },
  {
    "Id": 0,
    "Seasons": [
      "28f834e4-25bb-47e3-a7c7-f9089fbca86f"
    ],
    "Mal": {
      "Id": "46420",
      "Name": "Nanatsu no Taizai Movie 2: Hikari ni Norowareshi Mono-tachi",
      "ImageUrl": "https://cdn.myanimelist.net/images/anime/1096/113360.webp",
      "MemberCount": 37869,
      "Score": 713,
      "EpisodesCount": 1,
      "Status": 0
    }
  },
  {
    "Id": 0,
    "Seasons": [
      "28f834e4-25bb-47e3-a7c7-f9089fbca86f"
    ],
    "Mal": {
      "Id": "41497",
      "Name": "Fate/Grand Order: Shuukyoku Tokuiten - Kani Jikan Shinden Solomon",
      "ImageUrl": "https://cdn.myanimelist.net/images/anime/1507/114957.webp",
      "MemberCount": 34642,
      "Score": 725,
      "EpisodesCount": 1,
      "Status": 0
    }
  },
  {
    "Id": 0,
    "Seasons": [
      "28f834e4-25bb-47e3-a7c7-f9089fbca86f"
    ],
    "Mal": {
      "Id": "44586",
      "Name": "Kakushigoto Movie",
      "ImageUrl": "https://cdn.myanimelist.net/images/anime/1115/114953.webp",
      "MemberCount": 30154,
      "Score": 769,
      "EpisodesCount": 1,
      "Status": 0
    }
  },
  {
    "Id": 0,
    "Seasons": [
      "28f834e4-25bb-47e3-a7c7-f9089fbca86f"
    ],
    "Mal": {
      "Id": "44807",
      "Name": "Ryuu to Sobakasu no Hime",
      "ImageUrl": "https://cdn.myanimelist.net/images/anime/1081/115716.webp",
      "MemberCount": 28692,
      "Score": 753,
      "EpisodesCount": 1,
      "Status": 0
    }
  },
  {
    "Id": 0,
    "Seasons": [
      "28f834e4-25bb-47e3-a7c7-f9089fbca86f"
    ],
    "Mal": {
      "Id": "42030",
      "Name": "Fate/kaleid liner Prisma\u2606Illya Movie: Licht - Namae no Nai Shoujo",
      "ImageUrl": "https://cdn.myanimelist.net/images/anime/1331/117733.webp",
      "MemberCount": 20615,
      "Score": 690,
      "EpisodesCount": 1,
      "Status": 0
    }
  },
  {
    "Id": 0,
    "Seasons": [
      "28f834e4-25bb-47e3-a7c7-f9089fbca86f"
    ],
    "Mal": {
      "Id": "41471",
      "Name": "Kiniro Mosaic: Thank You!!",
      "ImageUrl": "https://cdn.myanimelist.net/images/anime/1505/116892.webp",
      "MemberCount": 8711,
      "Score": 0,
      "EpisodesCount": 1,
      "Status": 0
    }
  },
  {
    "Id": 0,
    "Seasons": [
      "28f834e4-25bb-47e3-a7c7-f9089fbca86f"
    ],
    "Mal": {
      "Id": "43755",
      "Name": "Misaki no Mayoiga",
      "ImageUrl": "https://cdn.myanimelist.net/images/anime/1472/116571.webp",
      "MemberCount": 8344,
      "Score": 0,
      "EpisodesCount": 1,
      "Status": 0
    }
  },
  {
    "Id": 0,
    "Seasons": [
      "28f834e4-25bb-47e3-a7c7-f9089fbca86f"
    ],
    "Mal": {
      "Id": "41140",
      "Name": "Princess Principal: Crown Handler Movie 2",
      "ImageUrl": "https://cdn.myanimelist.net/images/anime/1244/116570.webp",
      "MemberCount": 6214,
      "Score": 0,
      "EpisodesCount": 1,
      "Status": 0
    }
  },
  {
    "Id": 0,
    "Seasons": [
      "28f834e4-25bb-47e3-a7c7-f9089fbca86f"
    ],
    "Mal": {
      "Id": "38882",
      "Name": "Ryouma! The Prince of Tennis Shinsei Movie: Tennis no Ouji-sama",
      "ImageUrl": "https://cdn.myanimelist.net/images/anime/1737/117734.webp",
      "MemberCount": 3762,
      "Score": 0,
      "EpisodesCount": 1,
      "Status": 0
    }
  },
  {
    "Id": 0,
    "Seasons": [
      "28f834e4-25bb-47e3-a7c7-f9089fbca86f"
    ],
    "Mal": {
      "Id": "41462",
      "Name": "BanG Dream! Film Live 2nd Stage",
      "ImageUrl": "https://cdn.myanimelist.net/images/anime/1229/117735.webp",
      "MemberCount": 3755,
      "Score": 0,
      "EpisodesCount": 1,
      "Status": 0
    }
  },
  {
    "Id": 0,
    "Seasons": [
      "28f834e4-25bb-47e3-a7c7-f9089fbca86f"
    ],
    "Mal": {
      "Id": "49467",
      "Name": "Tomorrow\u0027s Leaves",
      "ImageUrl": "https://cdn.myanimelist.net/images/anime/1880/116886.webp",
      "MemberCount": 1486,
      "Score": 679,
      "EpisodesCount": 1,
      "Status": 0
    }
  },
  {
    "Id": 0,
    "Seasons": [
      "28f834e4-25bb-47e3-a7c7-f9089fbca86f"
    ],
    "Mal": {
      "Id": "44616",
      "Name": "Crayon Shin-chan Movie 29: Mystery Meki! Hana no Tenkasu Gakuen",
      "ImageUrl": "https://cdn.myanimelist.net/images/anime/1309/113382.webp",
      "MemberCount": 1175,
      "Score": 0,
      "EpisodesCount": 1,
      "Status": 0
    }
  },
  {
    "Id": 0,
    "Seasons": [
      "28f834e4-25bb-47e3-a7c7-f9089fbca86f"
    ],
    "Mal": {
      "Id": "43204",
      "Name": "Gundam: G no Reconguista Movie III - Uchuu kara no Isan",
      "ImageUrl": "https://cdn.myanimelist.net/images/anime/1192/117737.webp",
      "MemberCount": 1039,
      "Score": 0,
      "EpisodesCount": 1,
      "Status": 0
    }
  },
  {
    "Id": 0,
    "Seasons": [
      "28f834e4-25bb-47e3-a7c7-f9089fbca86f"
    ],
    "Mal": {
      "Id": "48352",
      "Name": "100-nichikan Ikita Wani",
      "ImageUrl": "https://cdn.myanimelist.net/images/anime/1871/115717.webp",
      "MemberCount": 717,
      "Score": 0,
      "EpisodesCount": 1,
      "Status": 0
    }
  },
  {
    "Id": 0,
    "Seasons": [
      "28f834e4-25bb-47e3-a7c7-f9089fbca86f"
    ],
    "Mal": {
      "Id": "49409",
      "Name": "Bai She II: Qing She Jie Qi",
      "ImageUrl": "https://cdn.myanimelist.net/images/anime/1024/116463.webp",
      "MemberCount": 556,
      "Score": 0,
      "EpisodesCount": 1,
      "Status": 0
    }
  },
  {
    "Id": 0,
    "Seasons": [
      "28f834e4-25bb-47e3-a7c7-f9089fbca86f"
    ],
    "Mal": {
      "Id": "49369",
      "Name": "Shinkai no Survival!",
      "ImageUrl": "https://cdn.myanimelist.net/images/anime/1681/116513.webp",
      "MemberCount": 178,
      "Score": 0,
      "EpisodesCount": 1,
      "Status": 0
    }
  },
  {
    "Id": 0,
    "Seasons": [
      "28f834e4-25bb-47e3-a7c7-f9089fbca86f"
    ],
    "Mal": {
      "Id": "49483",
      "Name": "Mini Dragon Specials",
      "ImageUrl": "https://cdn.myanimelist.net/images/anime/1100/116698.webp",
      "MemberCount": 23376,
      "Score": 764,
      "EpisodesCount": 8,
      "Status": 0
    }
  },
  {
    "Id": 0,
    "Seasons": [
      "28f834e4-25bb-47e3-a7c7-f9089fbca86f"
    ],
    "Mal": {
      "Id": "49297",
      "Name": "Isekai Cheat Magician: Yoiboshi no Matsuri to Majutsushi",
      "ImageUrl": "https://cdn.myanimelist.net/images/anime/1945/116050.webp",
      "MemberCount": 17627,
      "Score": 623,
      "EpisodesCount": 1,
      "Status": 0
    }
  },
  {
    "Id": 0,
    "Seasons": [
      "28f834e4-25bb-47e3-a7c7-f9089fbca86f"
    ],
    "Mal": {
      "Id": "49287",
      "Name": "Fumetsu no Anata e: Fushi no Tabiji",
      "ImageUrl": "https://cdn.myanimelist.net/images/anime/1130/116106.webp",
      "MemberCount": 12704,
      "Score": 656,
      "EpisodesCount": 1,
      "Status": 0
    }
  },
  {
    "Id": 0,
    "Seasons": [
      "28f834e4-25bb-47e3-a7c7-f9089fbca86f"
    ],
    "Mal": {
      "Id": "49550",
      "Name": "Bokutachi no Remake Recap",
      "ImageUrl": "https://cdn.myanimelist.net/images/anime/1776/117125.webp",
      "MemberCount": 7868,
      "Score": 607,
      "EpisodesCount": 1,
      "Status": 0
    }
  },
  {
    "Id": 0,
    "Seasons": [
      "28f834e4-25bb-47e3-a7c7-f9089fbca86f"
    ],
    "Mal": {
      "Id": "49138",
      "Name": "Princess Principal: Crown Handler Movie 1 - Busy Easy Money",
      "ImageUrl": "https://cdn.myanimelist.net/images/anime/1566/115608.webp",
      "MemberCount": 3850,
      "Score": 0,
      "EpisodesCount": 1,
      "Status": 0
    }
  },
  {
    "Id": 0,
    "Seasons": [
      "28f834e4-25bb-47e3-a7c7-f9089fbca86f"
    ],
    "Mal": {
      "Id": "48678",
      "Name": "Nomad: Megalo Box 2 Short Anime",
      "ImageUrl": "https://cdn.myanimelist.net/images/qm_50.gif",
      "MemberCount": 3082,
      "Score": 0,
      "EpisodesCount": 0,
      "Status": 0
    }
  },
  {
    "Id": 0,
    "Seasons": [
      "28f834e4-25bb-47e3-a7c7-f9089fbca86f"
    ],
    "Mal": {
      "Id": "49487",
      "Name": "Azur Lane: Bisoku Zenshin! Hokorashiki Bokou ni Shukusai wo",
      "ImageUrl": "https://cdn.myanimelist.net/images/anime/1476/116733.webp",
      "MemberCount": 3038,
      "Score": 673,
      "EpisodesCount": 1,
      "Status": 0
    }
  },
  {
    "Id": 0,
    "Seasons": [
      "28f834e4-25bb-47e3-a7c7-f9089fbca86f"
    ],
    "Mal": {
      "Id": "49290",
      "Name": "Magia Record: Mahou Shoujo Madoka\u2606Magica Gaiden (TV) Recaps",
      "ImageUrl": "https://cdn.myanimelist.net/images/anime/1275/116607.webp",
      "MemberCount": 2922,
      "Score": 592,
      "EpisodesCount": 3,
      "Status": 0
    }
  },
  {
    "Id": 0,
    "Seasons": [
      "28f834e4-25bb-47e3-a7c7-f9089fbca86f"
    ],
    "Mal": {
      "Id": "48627",
      "Name": "Hetalia World\u2605Stars Specials",
      "ImageUrl": "https://cdn.myanimelist.net/images/anime/1724/115681.webp",
      "MemberCount": 2753,
      "Score": 673,
      "EpisodesCount": 3,
      "Status": 0
    }
  },
  {
    "Id": 0,
    "Seasons": [
      "28f834e4-25bb-47e3-a7c7-f9089fbca86f"
    ],
    "Mal": {
      "Id": "49848",
      "Name": "Magia Record: Mahou Shoujo Madoka\u2606Magica Gaiden (TV) 2nd Season - Kakusei Zenya Recap",
      "ImageUrl": "https://cdn.myanimelist.net/images/anime/1887/117773.webp",
      "MemberCount": 2421,
      "Score": 592,
      "EpisodesCount": 1,
      "Status": 0
    }
  },
  {
    "Id": 0,
    "Seasons": [
      "28f834e4-25bb-47e3-a7c7-f9089fbca86f"
    ],
    "Mal": {
      "Id": "49396",
      "Name": "Kyoto Animation: Souzou-hen",
      "ImageUrl": "https://cdn.myanimelist.net/images/anime/1516/116475.webp",
      "MemberCount": 2182,
      "Score": 662,
      "EpisodesCount": 1,
      "Status": 0
    }
  },
  {
    "Id": 0,
    "Seasons": [
      "28f834e4-25bb-47e3-a7c7-f9089fbca86f"
    ],
    "Mal": {
      "Id": "49395",
      "Name": "Kyoto Animation: Meiji-hen",
      "ImageUrl": "https://cdn.myanimelist.net/images/anime/1470/116471.webp",
      "MemberCount": 1419,
      "Score": 648,
      "EpisodesCount": 1,
      "Status": 0
    }
  },
  {
    "Id": 0,
    "Seasons": [
      "28f834e4-25bb-47e3-a7c7-f9089fbca86f"
    ],
    "Mal": {
      "Id": "49348",
      "Name": "Blue Reflection Ray Special",
      "ImageUrl": "https://cdn.myanimelist.net/images/anime/1159/116282.webp",
      "MemberCount": 1077,
      "Score": 577,
      "EpisodesCount": 1,
      "Status": 0
    }
  },
  {
    "Id": 0,
    "Seasons": [
      "28f834e4-25bb-47e3-a7c7-f9089fbca86f"
    ],
    "Mal": {
      "Id": "49913",
      "Name": "Hachigatsu no Cinderella Nine Episode 13",
      "ImageUrl": "https://cdn.myanimelist.net/images/anime/1869/117974.webp",
      "MemberCount": 748,
      "Score": 640,
      "EpisodesCount": 1,
      "Status": 0
    }
  },
  {
    "Id": 0,
    "Seasons": [
      "28f834e4-25bb-47e3-a7c7-f9089fbca86f"
    ],
    "Mal": {
      "Id": "49442",
      "Name": "Propo Dance!",
      "ImageUrl": "https://cdn.myanimelist.net/images/anime/1991/117801.webp",
      "MemberCount": 72,
      "Score": 0,
      "EpisodesCount": 1,
      "Status": 0
    }
  },
  {
    "Id": 0,
    "Seasons": [
      "28f834e4-25bb-47e3-a7c7-f9089fbca86f"
    ],
    "Mal": {
      "Id": "49581",
      "Name": "Natsu ga Hajimaru.",
      "ImageUrl": "https://cdn.myanimelist.net/images/anime/1301/118370.webp",
      "MemberCount": 50,
      "Score": 0,
      "EpisodesCount": 1,
      "Status": 0
    }
  },
  {
    "Id": 0,
    "Seasons": [
      "28f834e4-25bb-47e3-a7c7-f9089fbca86f"
    ],
    "Mal": {
      "Id": "50046",
      "Name": "Yami Shibai: Furuido",
      "ImageUrl": "https://cdn.myanimelist.net/images/anime/1701/118616.webp",
      "MemberCount": 16,
      "Score": 0,
      "EpisodesCount": 1,
      "Status": 0
    }
  }
]